[
{
  "rates": {
    "CAD": 1.5202,
    "HKD": 8.3964,
    "ISK": 157.1,
    "PHP": 55.102,
    "DKK": 7.4548,
    "HUF": 353.39,
    "CZK": 27.61,
    "AUD": 1.6736,
    "RON": 4.8388,
    "SEK": 10.6103,
    "IDR": 16077.45,
    "INR": 82.1435,
    "BRL": 6.2701,
    "RUB": 78.908,
    "HRK": 7.558,
    "JPY": 116.31,
    "THB": 34.684,
    "CHF": 1.0521,
    "SGD": 1.5426,
    "PLN": 4.5596,
    "BGN": 1.9558,
    "TRY": 7.4276,
    "CNY": 7.7068,
    "NOK": 10.9663,
    "NZD": 1.8096,
    "ZAR": 19.8913,
    "USD": 1.0832,
    "MXN": 25.6337,
    "ILS": 3.8321,
    "GBP": 0.89153,
    "KRW": 1332.42,
    "MYR": 4.732
  },
  "base": "EUR",
  "date": "2020-05-18"
}
]